alloy/__init__.py
alloy/algo/__init__.py
alloy/algo/graph_search.py
alloy/controls/__init__.py
alloy/controls/state_machine.py
alloy/draw/__init__.py
alloy/draw/basic.py
alloy/interaction/__init__.py
alloy/interaction/dialog.py
alloy/math/__init__.py
alloy/math/basic.py
alloy/math/rotation_2D.py
alloy/math/vector_3D_op.py
alloy/robot/__init__.py
alloy/robot/baxter.py
alloy/ros/__init__.py
alloy/ros/basic.py
alloy/ros/ros_conversions.py
alloy/ros/roslibpy.py
alloy/ros/transform.py
alloy/spatial/__init__.py
alloy/spatial/primitives/__init__.py
alloy/spatial/primitives/box.py
alloy/spatial/primitives/line.py
alloy/spatial/primitives/polygon.py
alloy/spatial/primitives/ray.py
alloy/tools/__init__.py
alloy/tools/nlp.py
alloylib-0.3.0.dist-info/LICENSE
alloylib-0.3.0.dist-info/METADATA
alloylib-0.3.0.dist-info/WHEEL
alloylib-0.3.0.dist-info/top_level.txt
alloylib-0.3.0.dist-info/RECORD
