Metadata-Version: 2.1
Name: alloylib
Version: 0.3.0
Summary: Lab Library for Commonly used Modules/Functions
Home-page: https://github.com/CMU-TBD/alloy
Author: Xiang Zhi Tan
Author-email: zhi.tan@ri.cmu.edu
License: MIT
Platform: UNKNOWN
Requires-Dist: numpy
Requires-Dist: pyquaternion
Requires-Dist: scipy
